.DS_Store
particledist/MassDistribution.py
particledist/PFNDist.py
particledist/ParticleDistributionCMS.py
particledist/ParticleDistributionCMSEfficient.py
particledist/SignalInjectionTwoGluons.py
particledist/__init__.py
particledist-1.1.2.dist-info/LICENSE
particledist-1.1.2.dist-info/METADATA
particledist-1.1.2.dist-info/WHEEL
particledist-1.1.2.dist-info/top_level.txt
particledist-1.1.2.dist-info/RECORD
