Metadata-Version: 2.1
Name: particledist
Version: 1.1.2
Summary: Automate the search for new particles in event mass distributions
Home-page: https://github.com/nickchak21/particledist
Author: Nick Chakraborty
Author-email: nc165@duke.edu
License: UNKNOWN
Platform: UNKNOWN
Classifier: Programming Language :: Python :: 3
Classifier: License :: OSI Approved :: MIT License
Classifier: Operating System :: OS Independent
Requires-Python: >=3.5
Requires-Dist: numpy
Requires-Dist: matplotlib
Requires-Dist: scikit-learn
Requires-Dist: energyflow
Requires-Dist: h5py
Requires-Dist: POT
